ros_trajectory_msgs-5.5.1.data/data/include/trajectory_msgs/trajectory_msgs/msg/joint_trajectory.h
ros_trajectory_msgs-5.5.1.data/data/include/trajectory_msgs/trajectory_msgs/msg/joint_trajectory.hpp
ros_trajectory_msgs-5.5.1.data/data/include/trajectory_msgs/trajectory_msgs/msg/joint_trajectory_point.h
ros_trajectory_msgs-5.5.1.data/data/include/trajectory_msgs/trajectory_msgs/msg/joint_trajectory_point.hpp
ros_trajectory_msgs-5.5.1.data/data/include/trajectory_msgs/trajectory_msgs/msg/multi_dof_joint_trajectory.h
ros_trajectory_msgs-5.5.1.data/data/include/trajectory_msgs/trajectory_msgs/msg/multi_dof_joint_trajectory.hpp
ros_trajectory_msgs-5.5.1.data/data/include/trajectory_msgs/trajectory_msgs/msg/multi_dof_joint_trajectory_point.h
ros_trajectory_msgs-5.5.1.data/data/include/trajectory_msgs/trajectory_msgs/msg/multi_dof_joint_trajectory_point.hpp
ros_trajectory_msgs-5.5.1.data/data/include/trajectory_msgs/trajectory_msgs/msg/rosidl_generator_c__visibility_control.h
ros_trajectory_msgs-5.5.1.data/data/include/trajectory_msgs/trajectory_msgs/msg/rosidl_generator_cpp__visibility_control.hpp
ros_trajectory_msgs-5.5.1.data/data/include/trajectory_msgs/trajectory_msgs/msg/rosidl_typesupport_fastrtps_c__visibility_control.h
ros_trajectory_msgs-5.5.1.data/data/include/trajectory_msgs/trajectory_msgs/msg/rosidl_typesupport_fastrtps_cpp__visibility_control.h
ros_trajectory_msgs-5.5.1.data/data/include/trajectory_msgs/trajectory_msgs/msg/rosidl_typesupport_introspection_c__visibility_control.h
ros_trajectory_msgs-5.5.1.data/data/include/trajectory_msgs/trajectory_msgs/msg/detail/joint_trajectory__builder.hpp
ros_trajectory_msgs-5.5.1.data/data/include/trajectory_msgs/trajectory_msgs/msg/detail/joint_trajectory__description.c
ros_trajectory_msgs-5.5.1.data/data/include/trajectory_msgs/trajectory_msgs/msg/detail/joint_trajectory__functions.c
ros_trajectory_msgs-5.5.1.data/data/include/trajectory_msgs/trajectory_msgs/msg/detail/joint_trajectory__functions.h
ros_trajectory_msgs-5.5.1.data/data/lib/python3.14/site-packages/trajectory_msgs-5.5.1-py3.14.egg-info/PKG-INFO
ros_trajectory_msgs-5.5.1.data/data/lib/python3.14/site-packages/trajectory_msgs-5.5.1-py3.14.egg-info/SOURCES.txt
ros_trajectory_msgs-5.5.1.data/data/lib/python3.14/site-packages/trajectory_msgs-5.5.1-py3.14.egg-info/dependency_links.txt
ros_trajectory_msgs-5.5.1.data/data/lib/python3.14/site-packages/trajectory_msgs-5.5.1-py3.14.egg-info/top_level.txt
ros_trajectory_msgs-5.5.1.dist-info/METADATA
ros_trajectory_msgs-5.5.1.dist-info/WHEEL
ros_trajectory_msgs-5.5.1.dist-info/top_level.txt
ros_trajectory_msgs-5.5.1.dist-info/RECORD
ros_trajectory_msgs-5.5.1.dist-info/licenses/LICENSE
